pycolab/__init__.py
pycolab/ascii_art.py
pycolab/cropping.py
pycolab/engine.py
pycolab/human_ui.py
pycolab/plot.py
pycolab/rendering.py
pycolab/storytelling.py
pycolab/things.py
pycolab/examples/__init__.py
pycolab/examples/aperture.py
pycolab/examples/apprehend.py
pycolab/examples/better_scrolly_maze.py
pycolab/examples/extraterrestrial_marauders.py
pycolab/examples/fluvial_natation.py
pycolab/examples/hello_world.py
pycolab/examples/ordeal.py
pycolab/examples/scrolly_maze.py
pycolab/examples/shockwave.py
pycolab/examples/tennnnnnnnnnnnnnnnnnnnnnnnis.py
pycolab/examples/warehouse_manager.py
pycolab/examples/classics/__init__.py
pycolab/examples/classics/chain_walk.py
pycolab/examples/classics/cliff_walk.py
pycolab/examples/classics/four_rooms.py
pycolab/prefab_parts/__init__.py
pycolab/prefab_parts/drapes.py
pycolab/prefab_parts/sprites.py
pycolab/protocols/__init__.py
pycolab/protocols/logging.py
pycolab/protocols/scrolling.py
pycolab/tests/__init__.py
pycolab/tests/ascii_art_test.py
pycolab/tests/cropping_test.py
pycolab/tests/engine_test.py
pycolab/tests/maze_walker_test.py
pycolab/tests/scrolling_test.py
pycolab/tests/story_test.py
pycolab/tests/test_things.py
pycolab-1.2.dist-info/DESCRIPTION.rst
pycolab-1.2.dist-info/METADATA
pycolab-1.2.dist-info/RECORD
pycolab-1.2.dist-info/WHEEL
pycolab-1.2.dist-info/entry_points.txt
pycolab-1.2.dist-info/metadata.json
pycolab-1.2.dist-info/top_level.txt
pycolab-1.2.dist-info/zip-safe
