Metadata-Version: 2.0
Name: pycolab
Version: 1.2
Summary: An engine for small games for reinforcement learning agents.
Home-page: https://github.com/deepmind/pycolab/
Author: The pycolab authors
Author-email: pycolab@deepmind.com
License: Apache 2.0
Keywords: ai ascii art game engine gridworld reinforcement learning retro retrogaming
Platform: UNKNOWN
Classifier: Development Status :: 5 - Production/Stable
Classifier: Environment :: Console
Classifier: Environment :: Console :: Curses
Classifier: Intended Audience :: Developers
Classifier: Intended Audience :: Education
Classifier: Intended Audience :: Science/Research
Classifier: License :: OSI Approved :: Apache Software License
Classifier: Operating System :: MacOS :: MacOS X
Classifier: Operating System :: Microsoft :: Windows
Classifier: Operating System :: POSIX
Classifier: Operating System :: Unix
Classifier: Programming Language :: Python :: 2.7
Classifier: Programming Language :: Python :: 3.4
Classifier: Programming Language :: Python :: 3.5
Classifier: Programming Language :: Python :: 3.6
Classifier: Topic :: Games/Entertainment :: Arcade
Classifier: Topic :: Scientific/Engineering :: Artificial Intelligence
Classifier: Topic :: Software Development :: Libraries
Classifier: Topic :: Software Development :: Testing
Requires-Dist: numpy (>=1.9)
Requires-Dist: six
Provides-Extra: ndimage
Requires-Dist: scipy (>=0.13.3); extra == 'ndimage'
